wakis/__init__.py
wakis/bucket.py
wakis/logger.py
wakis/main.py
wakis/plotting.py
wakis/reader.py
wakis/simulation.py
wakis/solver.py
wakis-0.3.4.dist-info/LICENSE.txt
wakis-0.3.4.dist-info/METADATA
wakis-0.3.4.dist-info/WHEEL
wakis-0.3.4.dist-info/top_level.txt
wakis-0.3.4.dist-info/RECORD
