Metadata-Version: 2.1
Name: wakis
Version: 0.3.4
Summary: Wakis obtains Wake potential and Impedance from pre-computed fields
Home-page: https://github.com/ImpedanCEI/WAKIS
Author: Elena de la Fuente Garcia
Author-email: elena.de.la.fuente.garcia@cern.ch
Project-URL: Bug Tracker, https://github.com/ImpedanCEI/WAKIS/issues
Classifier: Development Status :: 3 - Alpha
Classifier: Intended Audience :: Developers
Classifier: Natural Language :: English
Classifier: Programming Language :: Python :: 3
Classifier: Operating System :: OS Independent
License-File: LICENSE.txt
Requires-Dist: matplotlib
Requires-Dist: numpy
Requires-Dist: h5py
